froxy/__about__.py
froxy/__init__.py
froxy/_const.py
froxy/_froxy.py
froxy/_storage.py
froxy-1.0.5.dist-info/LICENSE
froxy-1.0.5.dist-info/METADATA
froxy-1.0.5.dist-info/WHEEL
froxy-1.0.5.dist-info/top_level.txt
froxy-1.0.5.dist-info/RECORD
