Metadata-Version: 2.1
Name: froxy
Version: 1.0.5
Summary: Hide your IP with free proxies using Froxy
Home-page: https://github.com/matheusfelipeog/froxy
Author: Matheus Felipe
Author-email: matheusfelipeog@protonmail.com
License: MIT License
Project-URL: Bug Tracker, https://github.com/matheusfelipeog/froxy/issues
Project-URL: Documentation, https://github.com/matheusfelipeog/froxy/blob/master/README.md
Project-URL: Source Code, https://github.com/matheusfelipeog/froxy
Keywords: froxy,ip,hide ip,requests,proxy,free proxy,proxy list,proxies,free proxies,proxies list
Platform: UNKNOWN
Classifier: Development Status :: 5 - Production/Stable
Classifier: Intended Audience :: Developers
Classifier: Intended Audience :: Information Technology
Classifier: License :: OSI Approved :: MIT License
Classifier: Natural Language :: English
Classifier: Operating System :: OS Independent
Classifier: Programming Language :: Python
Classifier: Topic :: Software Development :: Libraries
Classifier: Topic :: Software Development :: Libraries :: Python Modules
Requires-Python: >=3.6
Requires-Dist: requests
